imgp.py
imgp-2.9.dist-info/LICENSE
imgp-2.9.dist-info/METADATA
imgp-2.9.dist-info/WHEEL
imgp-2.9.dist-info/entry_points.txt
imgp-2.9.dist-info/top_level.txt
imgp-2.9.dist-info/RECORD
