Metadata-Version: 2.1
Name: imgp
Version: 2.9
Summary: High-performance CLI batch image resizer & rotator
Home-page: https://github.com/jarun/imgp
Author: Arun Prakash Jana
Author-email: engineerarun@gmail.com
License: GPLv3
Keywords: image processing resize rotate optimize
Platform: any
Classifier: Development Status :: 5 - Production/Stable
Classifier: Environment :: Console
Classifier: Intended Audience :: Developers
Classifier: Intended Audience :: End Users/Desktop
Classifier: License :: OSI Approved :: GNU General Public License v3 (GPLv3)
Classifier: Natural Language :: English
Classifier: Operating System :: OS Independent
Classifier: Programming Language :: Python :: 3
Classifier: Programming Language :: Python :: 3 :: Only
Classifier: Programming Language :: Python :: 3.8
Classifier: Programming Language :: Python :: 3.9
Classifier: Programming Language :: Python :: 3.10
Classifier: Programming Language :: Python :: 3.11
Classifier: Topic :: Utilities
Requires-Python: >=3.8
License-File: LICENSE
Requires-Dist: pillow-simd
Provides-Extra: packaging
Requires-Dist: twine ; extra == 'packaging'
